Metadata-Version: 1.0
Name: Arni-distributions
Version: 1.2
Summary: Gaussian and Binomial distributions
Home-page: UNKNOWN
Author: Arni khede
Author-email: arnikhede03@gmail.com
License: UNKNOWN
Platform: UNKNOWN
